odin_messaging_bot/__init__.py
odin_messaging_bot/discord_bot.py
odin_messaging_bot/jetstream_bot.py
odin_messaging_bot/streaming_bot.py
odin_messaging_bot-0.1.13.dist-info/WHEEL
odin_messaging_bot-0.1.13.dist-info/METADATA
odin_messaging_bot-0.1.13.dist-info/RECORD
