Metadata-Version: 2.1
Name: odin-messaging-bot
Version: 0.1.13
Summary: A NATS/STAN Bot to publish/subscribe messages.
Author: adolfrodeno
Author-email: amvillalobos@uc.cl
Requires-Python: >=3.8,<4.0
Classifier: Programming Language :: Python :: 3
Classifier: Programming Language :: Python :: 3.10
Classifier: Programming Language :: Python :: 3.8
Classifier: Programming Language :: Python :: 3.9
Requires-Dist: aiohttp (>=3.3.1,<4.0.0)
Requires-Dist: asyncio-nats-client (==0.11.4)
Requires-Dist: asyncio-nats-streaming (>=0.4.0,<0.5.0)
Requires-Dist: nest-asyncio (>=1.5.1,<2.0.0)
Requires-Dist: pydantic (>=1.8.2,<2.0.0)
Requires-Dist: python-dotenv (>=0.19.1,<0.20.0)
Requires-Dist: ujson (>=5.1.0,<6.0.0)
